extreqs/__init__.py
extreqs/main.py
extreqs/version.py
extreqs-1.1.0.dist-info/LICENSE
extreqs-1.1.0.dist-info/METADATA
extreqs-1.1.0.dist-info/WHEEL
extreqs-1.1.0.dist-info/top_level.txt
extreqs-1.1.0.dist-info/RECORD
