Metadata-Version: 2.1
Name: extreqs
Version: 1.1.0
Summary: Parse python requirements.txt files into setuptools extras
Home-page: https://github.com/clbarnes/extreqs
Author: Chris L. Barnes
Classifier: Development Status :: 3 - Alpha
Classifier: License :: OSI Approved :: MIT License
Classifier: Programming Language :: Python :: 3
Classifier: Programming Language :: Python :: 3.7
Classifier: Programming Language :: Python :: 3.8
Classifier: Programming Language :: Python :: 3.9
Classifier: Programming Language :: Python :: 3.10
Requires-Python: >=3.7, <4.0
License-File: LICENSE
Requires-Dist: setuptools
